napalm_s350/__init__.py
napalm_s350/s350.py
napalm_s350-0.5.1.dist-info/LICENSE
napalm_s350-0.5.1.dist-info/METADATA
napalm_s350-0.5.1.dist-info/WHEEL
napalm_s350-0.5.1.dist-info/top_level.txt
napalm_s350-0.5.1.dist-info/RECORD
