Metadata-Version: 2.1
Name: napalm-s350
Version: 0.5.1
Summary: NAPALM driver for Cisco SMB switches (SF3xx, SF5xx, SG3xx, SG5xx)
Home-page: https://github.com/napalm-automation-community/napalm-s350
Author: Jasper Lievisse Adriaanse, Petr Klíma, Daniel Bacher
Author-email: j@jasper.la, qaxi@seznam.cz, mail@phill93.de
License: Apache 2.0
Classifier: Topic :: Utilities
Classifier: License :: OSI Approved :: Apache Software License
Classifier: Programming Language :: Python
Classifier: Programming Language :: Python :: 3
Classifier: Programming Language :: Python :: 3.8
Classifier: Programming Language :: Python :: 3.9
Classifier: Programming Language :: Python :: 3.10
Classifier: Programming Language :: Python :: 3.11
Classifier: Programming Language :: Python :: 3.12
Classifier: Programming Language :: Python :: 3.13
Classifier: Operating System :: POSIX :: Linux
Classifier: Operating System :: MacOS
License-File: LICENSE
Requires-Dist: napalm >=4.0.0
Requires-Dist: netmiko >=4.0.0
Requires-Dist: netaddr >=1.2.1
